dffml_model_xgboost/__init__.py
dffml_model_xgboost/version.py
dffml_model_xgboost/xgbclassifier.py
dffml_model_xgboost/xgbregressor.py
tests/__init__.py
tests/test_classifier_model.py
tests/test_regressor_model.py
dffml_model_xgboost-0.1.0.post0.dist-info/LICENSE
dffml_model_xgboost-0.1.0.post0.dist-info/METADATA
dffml_model_xgboost-0.1.0.post0.dist-info/WHEEL
dffml_model_xgboost-0.1.0.post0.dist-info/entry_points.txt
dffml_model_xgboost-0.1.0.post0.dist-info/top_level.txt
dffml_model_xgboost-0.1.0.post0.dist-info/RECORD
